step 4 counter/design.sv
// Code your design here
module counter(q,clk,reset);
  input clk,reset;
  output reg [3:0]q;
  
  always @(posedge clk )
    begin
      if (reset)
        q<=4'b0000;
      else 
        q<=q+3'b100;
    end 
endmodule

step 4 counter/testbench.sv
// Code your testbench here
// or browse Examples
module tb;
  reg clk,reset;
  wire [3:0]a;
  
  counter COUNTER1(.q(a),.clk(clk),.reset(reset));
  //counter COUNTER2(.q(b),.clk(clk),.clear(reset));
  
  initial begin
    
    $dumpfile("tff_wave.vcd");   
    $dumpvars(1, tb); 
    clk=0;
    reset=1;
    #20 reset =0;
    #60 reset=1;
    #90 reset=0;
    
   // #10 d=1;
    #300 $finish;
  end
    always #5 clk=~clk;
     //always #10 d=~d;
  
 
  
  
endmodule

step 4 counter/tff_wave.vcd
$date
	Mon Jul 27 04:02:00 2026
$end
$version
	Icarus Verilog
$end
$timescale
	1s
$end
$scope module tb $end
$var wire 4 ! a [3:0] $end
$var reg 1 " clk $end
$var reg 1 # reset $end
$upscope $end
$enddefinitions $end
$comment Show the parameter values. $end
$dumpall
$end
#0
$dumpvars
1#
0"
bx !
$end
#5
b0 !
1"
#10
0"
#15
1"
#20
0"
0#
#25
b100 !
1"
#30
0"
#35
b1000 !
1"
#40
0"
#45
b1100 !
1"
#50
0"
#55
b0 !
1"
#60
0"
#65
b100 !
1"
#70
0"
#75
b1000 !
1"
#80
0"
1#
#85
b0 !
1"
#90
0"
#95
1"
#100
0"
#105
1"
#110
0"
#115
1"
#120
0"
#125
1"
#130
0"
#135
1"
#140
0"
#145
1"
#150
0"
#155
1"
#160
0"
#165
1"
#170
0"
0#
#175
b100 !
1"
#180
0"
#185
b1000 !
1"
#190
0"
#195
b1100 !
1"
#200
0"
#205
b0 !
1"
#210
0"
#215
b100 !
1"
#220
0"
#225
b1000 !
1"
#230
0"
#235
b1100 !
1"
#240
0"
#245
b0 !
1"
#250
0"
#255
b100 !
1"
#260
0"
#265
b1000 !
1"
#270
0"
#275
b1100 !
1"
#280
0"
#285
b0 !
1"
#290
0"
#295
b100 !
1"
#300
0"
#305
b1000 !
1"
#310
0"
#315
b1100 !
1"
#320
0"
#325
b0 !
1"
#330
0"
#335
b100 !
1"
#340
0"
#345
b1000 !
1"
#350
0"
#355
b1100 !
1"
#360
0"
#365
b0 !
1"
#370
0"
#375
b100 !
1"
#380
0"
#385
b1000 !
1"
#390
0"
#395
b1100 !
1"
#400
0"
#405
b0 !
1"
#410
0"
#415
b100 !
1"
#420
0"
#425
b1000 !
1"
#430
0"
#435
b1100 !
1"
#440
0"
#445
b0 !
1"
#450
0"
#455
b100 !
1"
#460
0"
#465
b1000 !
1"
