up down counter/design.sv
module up_down_counter(
input clk,
  input reset,
  input up_down,
  output reg [3:0] count
);
  
  always @(posedge clk) begin
    
    if(reset)
      count<=4'b0000;
      else begin
        if(up_down)
        count<=count+1'b1;
        else
          count<=count-1'b1;
    end
    
    
  end
    
    endmodule

up down counter/testbench.sv
// Code your testbench here
// or browse Examples
module tb_up_down_counter;

reg clk;
reg reset;
reg up_down;
wire [3:0] count;

up_down_counter dut (
    .clk(clk),
    .reset(reset),
    .up_down(up_down),
    .count(count)
);


always #5 clk = ~clk;

initial begin
    clk = 0;
    reset = 1;
    up_down = 1;

  #10 reset = 0;    
  #50 up_down = 1;  // count up
   #50 up_down = 0;  // count down
   #50 $finish;
end
  initial begin
    $dumpfile("up_down_counter.vcd");
    $dumpvars(1, tb_up_down_counter);
  end

endmodule

up down counter/up_down_counter.vcd
$date
	Mon Jul 27 03:41:39 2026
$end
$version
	Icarus Verilog
$end
$timescale
	1s
$end
$scope module tb_up_down_counter $end
$var wire 4 ! count [3:0] $end
$var reg 1 " clk $end
$var reg 1 # reset $end
$var reg 1 $ up_down $end
$upscope $end
$enddefinitions $end
$comment Show the parameter values. $end
$dumpall
$end
#0
$dumpvars
1$
1#
0"
bx !
$end
#5
b0 !
1"
#10
0"
0#
#15
b1 !
1"
#20
0"
#25
b10 !
1"
#30
0"
#35
b11 !
1"
#40
0"
#45
b100 !
1"
#50
0"
#55
b101 !
1"
#60
0"
#65
b110 !
1"
#70
0"
#75
b111 !
1"
#80
0"
#85
b1000 !
1"
#90
0"
#95
b1001 !
1"
#100
0"
#105
b1010 !
1"
#110
0"
0$
#115
b1001 !
1"
#120
0"
#125
b1000 !
1"
#130
0"
#135
b111 !
1"
#140
0"
#145
b110 !
1"
#150
0"
#155
b101 !
1"
