step 3 counter/design.sv
// Code your design here
module counter(q,clk,reset);
  input clk,reset;
  output reg [3:0]q;
  
  always @(posedge clk )
    begin
      if (reset)
        q<=4'b0000;
      else 
        q<=q+2'b11;
    end 
endmodule

step 3 counter/testbench.sv
// Code your testbench here
// or browse Examples
module tb;
  reg clk,reset;
  wire [3:0]a;
  
  counter COUNTER1(.q(a),.clk(clk),.reset(reset));
  //counter COUNTER2(.q(b),.clk(clk),.clear(reset));
  
  initial begin
    
    $dumpfile("tff_wave.vcd");   
    $dumpvars(1, tb); 
    clk=0;
    reset=1;
    #20 reset =0;
    
   // #10 d=1;
    #300 $finish;
  end
    always #5 clk=~clk;
     //always #10 d=~d;
  
 
  
  
endmodule

step 3 counter/tff_wave.vcd
$date
	Mon Jul 27 04:03:43 2026
$end
$version
	Icarus Verilog
$end
$timescale
	1s
$end
$scope module tb $end
$var wire 4 ! a [3:0] $end
$var reg 1 " clk $end
$var reg 1 # reset $end
$upscope $end
$enddefinitions $end
$comment Show the parameter values. $end
$dumpall
$end
#0
$dumpvars
1#
0"
bx !
$end
#5
b0 !
1"
#10
0"
#15
1"
#20
0"
0#
#25
b11 !
1"
#30
0"
#35
b110 !
1"
#40
0"
#45
b1001 !
1"
#50
0"
#55
b1100 !
1"
#60
0"
#65
b1111 !
1"
#70
0"
#75
b10 !
1"
#80
0"
#85
b101 !
1"
#90
0"
#95
b1000 !
1"
#100
0"
#105
b1011 !
1"
#110
0"
#115
b1110 !
1"
#120
0"
#125
b1 !
1"
#130
0"
#135
b100 !
1"
#140
0"
#145
b111 !
1"
#150
0"
#155
b1010 !
1"
#160
0"
#165
b1101 !
1"
#170
0"
#175
b0 !
1"
#180
0"
#185
b11 !
1"
#190
0"
#195
b110 !
1"
#200
0"
#205
b1001 !
1"
#210
0"
#215
b1100 !
1"
#220
0"
#225
b1111 !
1"
#230
0"
#235
b10 !
1"
#240
0"
#245
b101 !
1"
#250
0"
#255
b1000 !
1"
#260
0"
#265
b1011 !
1"
#270
0"
#275
b1110 !
1"
#280
0"
#285
b1 !
1"
#290
0"
#295
b100 !
1"
#300
0"
#305
b111 !
1"
#310
0"
#315
b1010 !
1"
