Adder/design.sv

module full_adder(
    input a, b, cin,
    output sum, carry
);
    assign sum = a ^ b ^ cin;
    assign carry = (a & b) | (b & cin) | (cin & a);
endmodule


module ones_counter_3bit(
  input [2:0] x,
  output [1:0] y  
);
    wire s, c_out;

    full_adder fa (
      .a(x[0]),
      .b(x[1]),
      .cin(x[2]),
        .sum(s),
        .carry(c_out)
    );

    assign y[0] = s;
    assign y[1] = c_out;

endmodule

Adder/testbench.sv
`timescale 1ns/1ps

module tb;

  reg  [2:0] x;
  wire [1:0] y;

  ones_counter_3bit dut (
    .x(x),
    .y(y)
  );

  initial begin
    $display(" x    y (count of 1s)");
    $display("---------------------------");

    x = 3'b000; #10;
    $display(" %b %b", x, y);

    x = 3'b001; #10;
    $display(" %b %b",  x, y);

    x = 3'b010; #10;
    $display(" %b %b", x, y);

    x = 3'b011; #10;
    $display(" %b %b",  x, y);

    x = 3'b100; #10;
    $display(" %b %b",  x, y);

    x = 3'b101; #10;
    $display(" %b %b",  x, y);

    x = 3'b110; #10;
    $display(" %b %b",  x, y);

    x = 3'b111; #10;
    $display(" %b %b", x, y);

    $finish;
  end
  
  initial begin
    
    $dumpfile("ones_counter_3bit");
    $dumpvars(1,tb);
    
  end

endmodule

Adder/ones_counter_3bit.vcd
$date
	Mon Jul 27 06:06:25 2026
$end
$version
	Icarus Verilog
$end
$timescale
	1ps
$end
$scope module tb $end
$var wire 2 ! y [1:0] $end
$var reg 3 " x [2:0] $end
$upscope $end
$enddefinitions $end
$comment Show the parameter values. $end
$dumpall
$end
#0
$dumpvars
b0 "
b0 !
$end
#10000
b1 !
b1 "
#20000
b10 "
#30000
b10 !
b11 "
#40000
b1 !
b100 "
#50000
b10 !
b101 "
#60000
b110 "
#70000
b11 !
b111 "
