moore coin vending machine/design.sv
module vending_machine (
    input clk,
    input reset,
    input coin5,
    input coin10,
    output reg candy
);

 
//   parameter S0     = 3'b000,  
//             S5     = 3'b001, 
//             S10    = 3'b010, 
//             S5C    = 3'b011, 
//             S15  = 3'b100; 
  
  typedef enum reg [2:0] {
    S0=3'b000,
    S5=3'b001,
    S10=3'b010,
    S15=3'b011,
    S20=3'b100
} fsm_state_t;


   fsm_state_t state, next_state;
  reg [5:0] timer;          
     

 
  always @(posedge clk or posedge reset) begin
    if (reset)
      state <= S0;
    else
      state <= next_state;
  end

 
  always @(posedge clk or posedge reset) begin
    if (reset)
      timer <= 0;
    else if (state == S20)
      timer <= timer + 1;
    else
      timer <= 0;
  end

 
  always @(*) begin
    
    
//     next_state=state;
    case (state)

      S0: begin
        if (coin5)      next_state = S5;
        else if (coin10) next_state = S10;
        else  next_state = S0;
      end

    
      S5: begin
        if (coin5)      next_state = S10;
        else if (coin10) begin
       
          next_state = S15;  
        end
        else  next_state = S5;
      end

 
      S10: begin
        if (coin5) begin
       
          next_state = S15;  
        end
        else if (coin10) begin
          next_state = S20;
        end
        else  next_state = S10;
      end

  
      S15: begin
       
//         if (credit_from_20)
//           next_state = S5C;  
//         else
          next_state = S0;
        
    end

 
      S20: begin
       
        if (timer == 6'd60) begin
        
          next_state = S0; 
        end
        else if (coin10)
          next_state = S15; 
         else if (coin5)
           next_state = S10;
        else  next_state = S20;
      end

      default: next_state = S0;

    endcase
  end
  
 
  assign candy=(state== S15 || ((state==S20)&& (timer==0)))?1:0;
  

endmodule

moore coin vending machine/testbench.sv
// `timescale 1s/1s

module tb;

  reg clk;
  reg reset;
  reg coin5;
  reg coin10;
  wire candy;

  vending_machine DUT (
    .clk(clk),
    .reset(reset),
    .coin5(coin5),
    .coin10(coin10),
    .candy(candy)
  );

 
  always #1 clk = ~clk;

  initial begin
    clk    = 0;
    reset  = 1;
    coin5  = 0;
    coin10 = 0;

    #1 reset = 0;

  
         
    @(negedge clk) coin5  = 1;
    @(negedge clk) coin5  = 0;

    @(negedge clk) coin5  = 1;
    @(negedge clk) coin5  = 0;

    
    @(negedge clk) coin10 = 1;
    @(negedge clk) coin10 = 0;

    repeat (25) @(negedge clk);
    
    @(negedge clk) coin10 = 1;
    @(negedge clk) coin10 = 0;

  
    repeat (31) @(negedge clk);

 
    @(negedge clk) coin10 = 1;
    @(negedge clk) coin10 = 0;
    
          
    @(negedge clk) coin5  = 1;
    @(negedge clk) coin5  = 0;
    
           
    @(negedge clk) coin5  = 1;
    @(negedge clk) coin5  = 0;

    #10 $finish;
  end

  initial begin
    $dumpfile("vending_machine.vcd");
    $dumpvars(1,tb);
    $dumpvars(1,DUT.state);
    $dumpvars(1,DUT.timer);
  end

endmodule

moore coin vending machine/vending_machine.vcd
$date
	Mon Jul 27 06:00:34 2026
$end
$version
	Icarus Verilog
$end
$timescale
	1s
$end
$scope module tb $end
$var wire 1 ! candy $end
$var reg 1 " clk $end
$var reg 1 # coin10 $end
$var reg 1 $ coin5 $end
$var reg 1 % reset $end
$upscope $end
$scope module tb $end
$scope module DUT $end
$var reg 3 & state [2:0] $end
$upscope $end
$upscope $end
$scope module tb $end
$scope module DUT $end
$var reg 6 ' timer [5:0] $end
$upscope $end
$upscope $end
$enddefinitions $end
$comment Show the parameter values. $end
$dumpall
$end
#0
$dumpvars
b0 '
b0 &
1%
0$
0#
0"
0!
$end
#1
0%
1"
#2
1$
0"
#3
b1 &
1"
#4
0$
0"
#5
1"
#6
1$
0"
#7
b10 &
1"
#8
0$
0"
#9
1"
#10
1#
0"
#11
1!
b100 &
1"
#12
0#
0"
#13
0!
b1 '
1"
#14
0"
#15
b10 '
1"
#16
0"
#17
b11 '
1"
#18
0"
#19
b100 '
1"
#20
0"
#21
b101 '
1"
#22
0"
#23
b110 '
1"
#24
0"
#25
b111 '
1"
#26
0"
#27
b1000 '
1"
#28
0"
#29
b1001 '
1"
#30
0"
#31
b1010 '
1"
#32
0"
#33
b1011 '
1"
#34
0"
#35
b1100 '
1"
#36
0"
#37
b1101 '
1"
#38
0"
#39
b1110 '
1"
#40
0"
#41
b1111 '
1"
#42
0"
#43
b10000 '
1"
#44
0"
#45
b10001 '
1"
#46
0"
#47
b10010 '
1"
#48
0"
#49
b10011 '
1"
#50
0"
#51
b10100 '
1"
#52
0"
#53
b10101 '
1"
#54
0"
#55
b10110 '
1"
#56
0"
#57
b10111 '
1"
#58
0"
#59
b11000 '
1"
#60
0"
#61
b11001 '
1"
#62
0"
#63
b11010 '
1"
#64
1#
0"
#65
1!
b11011 '
b11 &
1"
#66
0#
0"
#67
0!
b0 &
b0 '
1"
