MOD 5 counter/design.sv
// Code your design here
module counter(q,clk,reset);
  input clk,reset;
  output reg [2:0]q;
  
  always @(posedge clk )
    begin
      if (reset)
        q<=4'b000;
      else if (q==4'b100)
        q<=4'b0000;
      else 
        q<=q+1;
    end 
endmodule

MOD 5 counter/testbench.sv
// Code your testbench here
// or browse Examples
module tb;
  reg clk,reset;
  wire [2:0]a;
  
  counter COUNTER1(.q(a),.clk(clk),.reset(reset));
  
  initial begin
    
    $dumpfile("tff_wave.vcd");   
    $dumpvars(1, tb); 
    clk=0;
    reset=1;
    #20 reset =0;
   
    #300 $finish;
  end
    always #5 clk=~clk;
  
endmodule

MOD 5 counter/tff_wave.vcd
$date
	Mon Jul 27 03:56:39 2026
$end
$version
	Icarus Verilog
$end
$timescale
	1s
$end
$scope module tb $end
$var wire 3 ! a [2:0] $end
$var reg 1 " clk $end
$var reg 1 # reset $end
$upscope $end
$enddefinitions $end
$comment Show the parameter values. $end
$dumpall
$end
#0
$dumpvars
1#
0"
bx !
$end
#5
b0 !
1"
#10
0"
#15
1"
#20
0"
0#
#25
b1 !
1"
#30
0"
#35
b10 !
1"
#40
0"
#45
b11 !
1"
#50
0"
#55
b100 !
1"
#60
0"
#65
b0 !
1"
#70
0"
#75
b1 !
1"
#80
0"
#85
b10 !
1"
#90
0"
#95
b11 !
1"
#100
0"
#105
b100 !
1"
#110
0"
#115
b0 !
1"
#120
0"
#125
b1 !
1"
#130
0"
#135
b10 !
1"
#140
0"
#145
b11 !
1"
#150
0"
#155
b100 !
1"
#160
0"
#165
b0 !
1"
#170
0"
#175
b1 !
1"
#180
0"
#185
b10 !
1"
#190
0"
#195
b11 !
1"
#200
0"
#205
b100 !
1"
#210
0"
#215
b0 !
1"
#220
0"
#225
b1 !
1"
#230
0"
#235
b10 !
1"
#240
0"
#245
b11 !
1"
#250
0"
#255
b100 !
1"
#260
0"
#265
b0 !
1"
#270
0"
#275
b1 !
1"
#280
0"
#285
b10 !
1"
#290
0"
#295
b11 !
1"
#300
0"
#305
b100 !
1"
#310
0"
#315
b0 !
1"
