MOD 16 counter/design.sv
// Code your design here
module counter(q,clk,reset);
  input clk,reset;
  output reg [3:0]q;
  
  always @(posedge clk )
    begin
      if (reset)
        q<=4'b000;
//       else if (q==4'b100)
//         q<=4'b0000;
      else 
        q<=q+1;
    end 
endmodule

MOD 16 counter/testbench.sv
// Code your testbench here
// or browse Examples
module tb;
  reg clk,reset;
  wire [3:0]a;
  
  counter COUNTER1(.q(a),.clk(clk),.reset(reset));
  
  initial begin
    
    $dumpfile("tff_wave.vcd");   
    $dumpvars(1, tb); 
    clk=0;
    reset=1;
    #20 reset =0;
    #250 reset=1;
    #20 reset=0;
   
    #300 $finish;
  end
    always #5 clk=~clk;
  
endmodule

MOD 16 counter/tff_wave.vcd
$date
	Mon Jul 27 04:09:53 2026
$end
$version
	Icarus Verilog
$end
$timescale
	1s
$end
$scope module tb $end
$var wire 4 ! a [3:0] $end
$var reg 1 " clk $end
$var reg 1 # reset $end
$upscope $end
$enddefinitions $end
$comment Show the parameter values. $end
$dumpall
$end
#0
$dumpvars
1#
0"
bx !
$end
#5
b0 !
1"
#10
0"
#15
1"
#20
0"
0#
#25
b1 !
1"
#30
0"
#35
b10 !
1"
#40
0"
#45
b11 !
1"
#50
0"
#55
b100 !
1"
#60
0"
#65
b101 !
1"
#70
0"
#75
b110 !
1"
#80
0"
#85
b111 !
1"
#90
0"
#95
b1000 !
1"
#100
0"
#105
b1001 !
1"
#110
0"
#115
b1010 !
1"
#120
0"
#125
b1011 !
1"
#130
0"
#135
b1100 !
1"
#140
0"
#145
b1101 !
1"
#150
0"
#155
b1110 !
1"
#160
0"
#165
b1111 !
1"
#170
0"
#175
b0 !
1"
#180
0"
#185
b1 !
1"
#190
0"
#195
b10 !
1"
#200
0"
#205
b11 !
1"
#210
0"
#215
b100 !
1"
#220
0"
#225
b101 !
1"
#230
0"
#235
b110 !
1"
#240
0"
#245
b111 !
1"
#250
0"
#255
b1000 !
1"
#260
0"
#265
b1001 !
1"
#270
0"
1#
#275
b0 !
1"
#280
0"
#285
1"
#290
0"
0#
#295
b1 !
1"
#300
0"
#305
b10 !
1"
#310
0"
#315
b11 !
1"
#320
0"
#325
b100 !
1"
#330
0"
#335
b101 !
1"
#340
0"
#345
b110 !
1"
#350
0"
#355
b111 !
1"
#360
0"
#365
b1000 !
1"
#370
0"
#375
b1001 !
1"
#380
0"
#385
b1010 !
1"
#390
0"
#395
b1011 !
1"
#400
0"
#405
b1100 !
1"
#410
0"
#415
b1101 !
1"
#420
0"
#425
b1110 !
1"
#430
0"
#435
b1111 !
1"
#440
0"
#445
b0 !
1"
#450
0"
#455
b1 !
1"
#460
0"
#465
b10 !
1"
#470
0"
#475
b11 !
1"
#480
0"
#485
b100 !
1"
#490
0"
#495
b101 !
1"
#500
0"
#505
b110 !
1"
#510
0"
#515
b111 !
1"
#520
0"
#525
b1000 !
1"
#530
0"
#535
b1001 !
1"
#540
0"
#545
b1010 !
1"
#550
0"
#555
b1011 !
1"
#560
0"
#565
b1100 !
1"
#570
0"
#575
b1101 !
1"
#580
0"
#585
b1110 !
1"
