moore sequence detector with random input/design.sv
// Code your design here
module seq_1011_moore (
    input clk,
    input reset,
    input x,
    output reg y
);

  reg [3:0] state, next_state;

  
  parameter IDEAL =4'b0000,
            S0 = 4'b0001,
            S1 = 4'b0010,
            S2 = 4'b0011,
            S3 = 4'b0100,
            S4 = 4'b0101,
            S5 = 4'b0110,
            S6 = 4'b0111,
            S7 = 4'b1000,
            S8 = 4'b1001;
 

  
  always @(posedge clk or reset) begin
    if (reset)
      state <= IDEAL;
    else
      state <= next_state;
  end

 
  always @(*) begin
    case (state)
      IDEAL: begin
        if (x) next_state = S1;
        else   next_state = S0;
      end
      
      S0: begin
        if (x) next_state = S2;
        else   next_state = S0;
      end
      
      S1: begin
        if (x) next_state = S3;
        else   next_state = S0;
      end

      S2: begin
        if (x) next_state = S3;
        else   next_state = S4;
      end

      S3: begin
        if (x) next_state = S5;
        else   next_state = S0;
      end

      S4: begin
        if (x) next_state = S6; 
        else   next_state = S0;
      end
      
      S5: begin
        if (x) next_state = S7; 
        else   next_state = S0;
      end
      
      S6: begin
        if (x) next_state = S3; 
        else   next_state = S4;
      end
      
      S7: begin
        if (x) next_state = S7;
        else   next_state = S0;
      end

      default: next_state = IDEAL;
    endcase
  end

  
  always @(*) begin
    if (state == S6 || state == S7)
      y = 1;
    else
      y = 0;
  end

endmodule

moore sequence detector with random input/testbench.sv
// Code your testbench here
// or browse Examples
module tb;

  reg clk_;
  reg reset_;
  reg x_;
  wire y_;

  seq_1011_moore DUT (
    .clk (clk_),
    .reset (reset_),
    .x (x_),
    .y (y_)
  );

 
  always #5 clk_ = ~clk_;

  integer i;

  initial begin
    clk_ = 0;
    reset_ = 1;
    x_  = 0;

  
  #12 reset_ = 0;

    for (i = 0; i < 30; i = i + 1) begin
      @(negedge clk_);
      x_ = $random % 2;  
    end

   #20 $finish;
  end

  initial begin
    $dumpfile("seq_1011_moore.vcd");
    $dumpvars(1, tb);
  end

endmodule

moore sequence detector with random input/seq_1011_moore.vcd
$date
	Mon Jul 27 05:51:26 2026
$end
$version
	Icarus Verilog
$end
$timescale
	1s
$end
$scope module tb $end
$var wire 1 ! y_ $end
$var reg 1 " clk_ $end
$var reg 1 # reset_ $end
$var reg 1 $ x_ $end
$var integer 32 % i [31:0] $end
$upscope $end
$enddefinitions $end
$comment Show the parameter values. $end
$dumpall
$end
#0
$dumpvars
bx %
0$
1#
0"
0!
$end
#5
1"
#10
0"
#12
b0 %
0#
#15
1"
#20
b1 %
0"
#25
1"
#30
b10 %
1$
0"
#35
1"
#40
b11 %
0"
#45
1"
#50
b100 %
0"
#55
1"
#60
b101 %
0"
#65
1!
1"
#70
b110 %
0"
#75
1"
#80
b111 %
0"
#85
1"
#90
b1000 %
0$
0"
#95
0!
1"
#100
b1001 %
1$
0"
#105
1"
#110
b1010 %
0"
#115
1"
#120
b1011 %
0$
0"
#125
1"
#130
b1100 %
1$
0"
#135
1"
#140
b1101 %
0"
#145
1"
#150
b1110 %
0$
0"
#155
1"
#160
b1111 %
1$
0"
#165
1"
#170
b10000 %
0$
0"
#175
1"
#180
b10001 %
1$
0"
#185
1!
1"
#190
b10010 %
0$
0"
#195
0!
1"
#200
b10011 %
1$
0"
#205
1!
1"
#210
b10100 %
0"
#215
0!
1"
#220
b10101 %
0$
0"
#225
1"
#230
b10110 %
1$
0"
#235
1"
#240
b10111 %
0$
0"
#245
1"
#250
b11000 %
0"
#255
1"
#260
b11001 %
0"
#265
1"
#270
b11010 %
1$
0"
#275
1"
#280
b11011 %
0$
0"
#285
1"
#290
b11100 %
1$
0"
#295
1!
1"
#300
b11101 %
0"
#305
0!
1"
#310
b11110 %
0"
#315
1"
#320
0"
#325
1!
1"
