fsm sequence detector melay non-overlappin/design.sv
// Code your design here
module seq_1011_detector (
    input clk,
    input reset,
    input x,
    output reg y
);

  reg [1:0] current_state, next_state;

  
  parameter S0 = 2'b00,
            S1 = 2'b01,
            S2 = 2'b10,
            S3 = 2'b11;

  
  always @(posedge clk or posedge reset) begin
    if (reset)
      current_state <= S0;
    else
      current_state <= next_state;
  end

 
  always @(*) begin
    y = 0;
    case (current_state)
      S0: begin
        if (x) next_state = S1;
        else   next_state = S0;
      end

      S1: begin
        if (x) next_state = S1;
        else   next_state = S2;
      end

      S2: begin
        if (x) next_state = S3;
        else   next_state = S0;
      end

      S3: begin
        if (x) begin
          next_state = S0; // non overlap
          y = 1;           // 1011 detected
        end else
          next_state = S0;
      end

      default: next_state = S0;
    endcase
  end

endmodule

fsm sequence detector melay non-overlappin/testbench.sv
// Code your testbench here
// or browse Examples
module tb;

  reg clk;
  reg reset;
  reg x;
  wire y;

  seq_1011_detector DUT (
    .clk(clk),
    .reset(reset),
    .x(x),
    .y(y)
  );

  always #5 clk = ~clk;

  initial begin
    clk = 0;
    reset = 1;
    x = 0;

    #10 reset = 0;

    #10 x = 1;
    #10 x = 0;
    #10 x = 1;
    #10 x = 1;  // first detection

    #10 x = 0;
    #10 x = 1;
    #10 x = 1;
    #10 x = 0;
    #10 x = 1;
    #10 x = 1;// second detection

    #20 $finish;
  end

  initial begin
    $dumpfile("seq_1011.vcd");
    $dumpvars(1, tb);
  end

endmodule

fsm sequence detector melay non-overlappin/seq_1011.vcd
$date
	Mon Jul 27 02:52:06 2026
$end
$version
	Icarus Verilog
$end
$timescale
	1s
$end
$scope module tb $end
$var wire 1 ! y $end
$var reg 1 " clk $end
$var reg 1 # reset $end
$var reg 1 $ x $end
$upscope $end
$enddefinitions $end
$comment Show the parameter values. $end
$dumpall
$end
#0
$dumpvars
0$
1#
0"
0!
$end
#5
1"
#10
0"
0#
#15
1"
#20
0"
1$
#25
1"
#30
0"
0$
#35
1"
#40
0"
1$
#45
1!
1"
#50
0"
#55
0!
1"
#60
0"
0$
#65
1"
#70
0"
1$
#75
1"
#80
0"
#85
1"
#90
0"
0$
#95
1"
#100
0"
1$
#105
1!
1"
#110
0"
#115
0!
1"
