ab counter/design.sv
module en_counter (
    input clk,
    input reset,
    input enable,
  output reg  [3:0] q
);

always @(posedge clk) begin
    if (reset)
        q <= 4'b0000;
    else if (enable)
        q <= q + 1'b1;
    else
        q <= q;  
end

endmodule

module dut (
    input  clk,
    input  reset,
    input  A,
    input  B,
    output reg [3:0] out,       
    output reg [3:0] count_a,   
    output reg [3:0] count_b,   
    output reg [3:0] diff       
);

reg en;

always @(posedge clk) begin
    if (reset)
        en <= 1'b0;
  else if (A)
        en <= 1'b1;
    else if (B)
        en <= 1'b0;
end

en_counter u1 (
    .clk(clk),
    .reset(reset),
    .enable(en),
    .q(out)
);

always @(posedge clk) begin
    if (reset) begin
        count_a <= 4'b0000;
        count_b <= 4'b0000;
        diff    <= 4'b0000;
    end
    else begin
        if (A)
            count_a <= out;        

        if (B) begin
            count_b <= out;        
            diff    <= out - count_a;
        end
    end
end

endmodule

ab counter/testbench.sv
module tb;

reg clk, reset, A, B;
  wire [3:0] OUT;
  wire [3:0] count_a;
wire [3:0] count_b;
wire [3:0] diff;

dut ab1 (
    .clk(clk),
    .reset(reset),
    .A(A),
    .B(B),
  .out(OUT),
  .count_a(count_a),
    .count_b(count_b),
    .diff(diff)
);

always #5 clk = ~clk;

initial begin
    $dumpfile("ab_counter.vcd");
  $dumpvars(1, tb);

    clk = 0;
    reset = 1;
    A = 0;
    B = 0;

    #10 reset = 0;
    #25 A = 1;
    #5  A = 0;
    #65 B = 1;
    #5  B = 0;
     #25 A = 1;
    #5  A = 0;
   #65 B = 1;
    #5  B = 0;
  
    #20 $finish;
end

endmodule

ab counter/ab_counter.vcd
$date
	Mon Jul 27 05:35:58 2026
$end
$version
	Icarus Verilog
$end
$timescale
	1s
$end
$scope module tb $end
$var wire 4 ! diff [3:0] $end
$var wire 4 " count_b [3:0] $end
$var wire 4 # count_a [3:0] $end
$var wire 4 $ OUT [3:0] $end
$var reg 1 % A $end
$var reg 1 & B $end
$var reg 1 ' clk $end
$var reg 1 ( reset $end
$upscope $end
$enddefinitions $end
$comment Show the parameter values. $end
$dumpall
$end
#0
$dumpvars
1(
0'
0&
0%
bx $
bx #
bx "
bx !
$end
#5
b0 $
b0 !
b0 "
b0 #
1'
#10
0'
0(
#15
1'
#20
0'
#25
1'
#30
0'
#35
1'
1%
#40
0'
0%
#45
b1 $
1'
#50
0'
#55
b10 $
1'
#60
0'
#65
b11 $
1'
#70
0'
#75
b100 $
1'
#80
0'
#85
b101 $
1'
#90
0'
#95
b110 $
1'
#100
0'
#105
b111 $
b110 !
b110 "
1'
1&
#110
0'
0&
#115
1'
#120
0'
#125
1'
#130
0'
#135
b111 #
1'
1%
#140
0'
0%
#145
b1000 $
1'
#150
0'
#155
b1001 $
1'
#160
0'
#165
b1010 $
1'
#170
0'
#175
b1011 $
1'
#180
0'
#185
b1100 $
1'
#190
0'
#195
b1101 $
1'
#200
0'
#205
b1110 $
b1101 "
1'
1&
#210
0'
0&
