traffic controller fsm/design.sv
module traffic_controller (
  input  clk,
   input  reset,
  input  NScar,
  input  EWcar,
   output reg NSlite,
   output reg EWlite
 
);

reg state,next_state;        
reg [4:0] count;  
  wire s_change;


always @(posedge clk or posedge reset) begin
    if (reset)
        count <= 5'd0;
    else if (count == 5'd29)
        count <= 5'd0;
    else
        count <= count + 1'b1;
end



always @(posedge clk or posedge reset) begin
    if (reset)
        state <= 1'b0; 
  else if(s_change==1) 
       state<=next_state;
    
end

always @(*) begin
    case (state)
        1'b0: begin 
          if (EWcar)
                next_state = 1'b1;
           else
               next_state = 1'b0;
        end

        1'b1: begin 
          if (!NScar)
                next_state = 1'b1;
            else
                next_state = 1'b0;
        end
    endcase
end


  
always @(*) begin
    if (state == 1'b0) begin
        NSlite = 1'b1;
        EWlite = 1'b0;
    end
    else begin
        NSlite = 1'b0;
        EWlite = 1'b1;
    end
end

  assign  s_change=(count==29)?1:0;
 

endmodule

traffic controller fsm/testbench.sv
module tb;

reg clk, reset;
reg NScar, EWcar;
wire NSlite, EWlite;


traffic_controller dut (
  .clk(clk),
    .reset(reset),
    .NScar(NScar),
    .EWcar(EWcar),
    .NSlite(NSlite),
    .EWlite(EWlite)
   
);

always #5 clk = ~clk;

initial begin
   
  $monitor("T=%0t NS=%b EW=%b  NScar=%b EWcar=%b",
              $time,  NSlite, EWlite, NScar, EWcar);

 clk = 0;
 reset = 1;
NScar = 0;
EWcar = 0;

 #10 reset = 0;

#70  EWcar = 1;  
#240 EWcar = 0;

 #90  NScar = 1;
 #200 NScar = 0;
  
  #60  EWcar = 1;
  #10  NScar = 1;

 #700 $finish;
end
  initial begin
   $dumpfile("traffic.vcd");
    $dumpvars(1, dut);
  end


endmodule

traffic controller fsm/traffic.vcd
$date
	Mon Jul 27 05:45:46 2026
$end
$version
	Icarus Verilog
$end
$timescale
	1s
$end
$scope module tb $end
$scope module dut $end
$var wire 1 ! EWcar $end
$var wire 1 " NScar $end
$var wire 1 # clk $end
$var wire 1 $ reset $end
$var wire 1 % s_change $end
$var reg 1 & EWlite $end
$var reg 1 ' NSlite $end
$var reg 5 ( count [4:0] $end
$var reg 1 ) next_state $end
$var reg 1 * state $end
$upscope $end
$upscope $end
$enddefinitions $end
$comment Show the parameter values. $end
$dumpall
$end
#0
$dumpvars
0*
0)
b0 (
1'
0&
0%
1$
0#
0"
0!
$end
#5
1#
#10
0#
0$
#15
b1 (
1#
#20
0#
#25
b10 (
1#
#30
0#
#35
b11 (
1#
#40
0#
#45
b100 (
1#
#50
0#
#55
b101 (
1#
#60
0#
#65
b110 (
1#
#70
0#
#75
b111 (
1#
#80
1)
0#
1!
#85
b1000 (
1#
#90
0#
#95
b1001 (
1#
#100
0#
#105
b1010 (
1#
#110
0#
#115
b1011 (
1#
#120
0#
#125
b1100 (
1#
#130
0#
#135
b1101 (
1#
#140
0#
#145
b1110 (
1#
#150
0#
#155
b1111 (
1#
#160
0#
#165
b10000 (
1#
#170
0#
#175
b10001 (
1#
#180
0#
#185
b10010 (
1#
#190
0#
#195
b10011 (
1#
#200
0#
#205
b10100 (
1#
#210
0#
#215
b10101 (
1#
#220
0#
#225
b10110 (
1#
#230
0#
#235
b10111 (
1#
#240
0#
#245
b11000 (
1#
#250
0#
#255
b11001 (
1#
#260
0#
#265
b11010 (
1#
#270
0#
#275
b11011 (
1#
#280
0#
#285
b11100 (
1#
#290
0#
#295
1%
b11101 (
1#
#300
0#
#305
0%
1&
0'
1*
b0 (
1#
#310
0#
#315
b1 (
1#
#320
0#
0!
#325
b10 (
1#
#330
0#
#335
b11 (
1#
#340
0#
#345
b100 (
1#
#350
0#
#355
b101 (
1#
#360
0#
#365
b110 (
1#
#370
0#
#375
b111 (
1#
#380
0#
#385
b1000 (
1#
#390
0#
#395
b1001 (
1#
#400
0#
#405
b1010 (
1#
#410
0)
0#
1"
#415
b1011 (
1#
#420
0#
#425
b1100 (
1#
#430
0#
#435
b1101 (
1#
#440
0#
#445
b1110 (
1#
#450
0#
#455
b1111 (
1#
#460
0#
#465
b10000 (
1#
#470
0#
#475
b10001 (
1#
#480
0#
#485
b10010 (
1#
#490
0#
#495
b10011 (
1#
#500
0#
#505
b10100 (
1#
#510
0#
#515
b10101 (
1#
#520
0#
#525
b10110 (
1#
#530
0#
#535
b10111 (
1#
#540
0#
#545
b11000 (
1#
#550
0#
#555
b11001 (
1#
#560
0#
#565
b11010 (
1#
#570
0#
#575
b11011 (
1#
#580
0#
#585
b11100 (
1#
#590
0#
#595
1%
b11101 (
1#
#600
0#
#605
0%
0&
1'
0*
b0 (
1#
#610
0#
0"
#615
b1 (
1#
#620
0#
#625
b10 (
1#
#630
0#
#635
b11 (
1#
#640
0#
#645
b100 (
1#
#650
0#
#655
b101 (
1#
#660
0#
#665
b110 (
1#
#670
1)
0#
1!
#675
b111 (
1#
#680
0#
1"
#685
b1000 (
1#
#690
0#
#695
b1001 (
1#
#700
0#
#705
b1010 (
1#
#710
0#
#715
b1011 (
1#
#720
0#
#725
b1100 (
1#
#730
0#
#735
b1101 (
1#
#740
0#
#745
b1110 (
1#
#750
0#
#755
b1111 (
1#
#760
0#
#765
b10000 (
1#
#770
0#
#775
b10001 (
1#
#780
0#
#785
b10010 (
1#
#790
0#
#795
b10011 (
1#
#800
0#
#805
b10100 (
1#
#810
0#
#815
b10101 (
1#
#820
0#
#825
b10110 (
1#
#830
0#
#835
b10111 (
1#
#840
0#
#845
b11000 (
1#
#850
0#
#855
b11001 (
1#
#860
0#
#865
b11010 (
1#
#870
0#
#875
b11011 (
1#
#880
0#
#885
b11100 (
1#
#890
0#
#895
1%
b11101 (
1#
#900
0#
#905
0%
1&
0'
0)
1*
b0 (
1#
#910
0#
#915
b1 (
1#
#920
0#
#925
b10 (
1#
#930
0#
#935
b11 (
1#
#940
0#
#945
b100 (
1#
#950
0#
#955
b101 (
1#
#960
0#
#965
b110 (
1#
#970
0#
#975
b111 (
1#
#980
0#
#985
b1000 (
1#
#990
0#
#995
b1001 (
1#
#1000
0#
#1005
b1010 (
1#
#1010
0#
#1015
b1011 (
1#
#1020
0#
#1025
b1100 (
1#
#1030
0#
#1035
b1101 (
1#
#1040
0#
#1045
b1110 (
1#
#1050
0#
#1055
b1111 (
1#
#1060
0#
#1065
b10000 (
1#
#1070
0#
#1075
b10001 (
1#
#1080
0#
#1085
b10010 (
1#
#1090
0#
#1095
b10011 (
1#
#1100
0#
#1105
b10100 (
1#
#1110
0#
#1115
b10101 (
1#
#1120
0#
#1125
b10110 (
1#
#1130
0#
#1135
b10111 (
1#
#1140
0#
#1145
b11000 (
1#
#1150
0#
#1155
b11001 (
1#
#1160
0#
#1165
b11010 (
1#
#1170
0#
#1175
b11011 (
1#
#1180
0#
#1185
b11100 (
1#
#1190
0#
#1195
1%
b11101 (
1#
#1200
0#
#1205
0%
0&
1'
1)
0*
b0 (
1#
#1210
0#
#1215
b1 (
1#
#1220
0#
#1225
b10 (
1#
#1230
0#
#1235
b11 (
1#
#1240
0#
#1245
b100 (
1#
#1250
0#
#1255
b101 (
1#
#1260
0#
#1265
b110 (
1#
#1270
0#
#1275
b111 (
1#
#1280
0#
#1285
b1000 (
1#
#1290
0#
#1295
b1001 (
1#
#1300
0#
#1305
b1010 (
1#
#1310
0#
#1315
b1011 (
1#
#1320
0#
#1325
b1100 (
1#
#1330
0#
#1335
b1101 (
1#
#1340
0#
#1345
b1110 (
1#
#1350
0#
#1355
b1111 (
1#
#1360
0#
#1365
b10000 (
1#
#1370
0#
#1375
b10001 (
1#
