lift fsm/design.sv
// Code your design here
module lift_fsm (
    input clk,
    input reset,
    input [1:0] req_floor,  
    output reg [1:0] current_floor
);

always @(posedge clk or posedge reset) begin
    if (reset)
        current_floor <= 2'b00; 
    else begin
        if (req_floor > current_floor)
            current_floor <= current_floor + 1'b1; 
        else if (req_floor < current_floor)
            current_floor <= current_floor - 1'b1;
        else
            current_floor <= current_floor;
    end
end

endmodule

lift fsm/testbench.sv
// Code your testbench here
// or browse Examples
module tb;

reg clk, reset;
reg [1:0] req_floor;
wire [1:0] current_floor;

lift_fsm dut (
    .clk(clk),
    .reset(reset),
    .req_floor(req_floor),
    .current_floor(current_floor)
);

always #5 clk = ~clk;

initial begin
    $dumpfile("lift_fsm.vcd");
  $dumpvars(1, tb);

    clk = 0;
    reset = 1;
    req_floor = 2'b00; 
    #10;

    reset = 0;

    
    req_floor = 2'b01;
    #30;

    req_floor = 2'b00;
    #30;

    req_floor = 2'b11;
    #30;

    req_floor = 2'b00;
    #30;
   
    $finish;
end

endmodule

lift fsm/lift_fsm.vcd
$date
	Mon Jul 27 05:43:44 2026
$end
$version
	Icarus Verilog
$end
$timescale
	1s
$end
$scope module tb $end
$var wire 2 ! current_floor [1:0] $end
$var reg 1 " clk $end
$var reg 2 # req_floor [1:0] $end
$var reg 1 $ reset $end
$upscope $end
$enddefinitions $end
$comment Show the parameter values. $end
$dumpall
$end
#0
$dumpvars
1$
b0 #
0"
b0 !
$end
#5
1"
#10
0"
b1 #
0$
#15
b1 !
1"
#20
0"
#25
1"
#30
0"
#35
1"
#40
0"
b0 #
#45
b0 !
1"
#50
0"
#55
1"
#60
0"
#65
1"
#70
0"
b11 #
#75
b1 !
1"
#80
0"
#85
b10 !
1"
#90
0"
#95
b11 !
1"
#100
0"
b0 #
#105
b10 !
1"
#110
0"
#115
b1 !
1"
#120
0"
#125
b0 !
1"
