ALU/design.sv
// Code your design here

`timescale 1ns / 1ps

module alu_8bit (
    input  [7:0] a, b,       
    input  [2:0] sel,    
    output reg [7:0] result, 
    output zero              
);

    assign zero = (result == 8'b0);

    always @(*) begin
        case(sel)
            3'b000: result = a + b;       // Addition
            3'b001: result = a - b;       // Subtraction
            3'b010: result = a & b;       // Bitwise AND
            3'b011: result = a | b;       // Bitwise OR
            3'b100: result = a ^ b;       // Bitwise XOR
            3'b101: result = ~a;    // not
            3'b110: result = (a < b) ? 8'd1 : 8'd0; // Less Than
            3'b111: result = a << 1;      // Logical Shift Left
            default: result = a + b;
        endcase
    end

endmodule

ALU/testbench.sv
// Code your testbench here
// or browse Examples
`timescale 1ns / 1ps  

module tb;

   
    reg  [7:0] a, b;
    reg  [2:0] sel;
    wire [7:0] result;
    wire       zero;

   
    alu_8bit dut (
      .a(a), 
        .b(b),
        .sel(sel),
        .result(result),
        .zero(zero)
    );

    initial begin
      
        $monitor("%0t\t %d \t %d \t %b \t %d \t\t %b", $time, a, b, sel, result, zero);

       
//         a = 8'd2; b = 8'd3; sel = 3'b000;
//         #10; 
      
//          a = 8'b0000_1010; b = 8'b0000_1100; sel = 3'b100;
//         #10;

        
//         a = 8'd5; b = 8'd5; sel = 3'b001;
//         #10;

      
      a = 4'b1010; b = 4'b0011;

    sel = 3'b000; #10; 
    sel = 3'b001; #10; 
    sel = 3'b010; #10; 
    sel = 3'b011; #10; 
    sel = 3'b100; #10; 
    sel = 3'b101; #10; 
    sel = 3'b110; #10; 
    sel = 3'b111; #10; 
       
        #10;

        $finish; 
    end
  
   
  initial
    begin
      $dumpfile("alu_8bit.vcd");
      $dumpvars(1,tb);       
    end

endmodule

ALU/alu_8bit.vcd
$date
	Mon Jul 27 06:38:08 2026
$end
$version
	Icarus Verilog
$end
$timescale
	1ps
$end
$scope module tb $end
$var wire 1 ! zero $end
$var wire 8 " result [7:0] $end
$var reg 8 # a [7:0] $end
$var reg 8 $ b [7:0] $end
$var reg 3 % sel [2:0] $end
$upscope $end
$enddefinitions $end
$comment Show the parameter values. $end
$dumpall
$end
#0
$dumpvars
b0 %
b11 $
b1010 #
b1101 "
0!
$end
#10000
b111 "
b1 %
#20000
b10 "
b10 %
#30000
b1011 "
b11 %
#40000
b1001 "
b100 %
#50000
b11110101 "
b101 %
#60000
1!
b0 "
b110 %
#70000
0!
b10100 "
b111 %
