syn down counter/design.sv
// Code your design here
module counter(q,clk,clear);
  input clk,clear;
  output reg [3:0]q;
  
  always @(posedge clk )
    begin
      if (clear)
        q<=4'b1111;
      else 
        q<=q-1;
    end 
endmodule

syn down counter/testbench.sv
// Code your testbench here
// or browse Examples
module tb;
  reg clk,reset;
  wire [3:0]a;
  
  counter COUNTER1(.q(a),.clk(clk),.clear(reset));
  //counter COUNTER2(.q(b),.clk(clk),.clear(reset));
  
  initial begin
    
    $dumpfile("tff_wave.vcd");  
    $dumpvars(1, tb); 
    clk=0;
   #10 reset=1;
    #20 reset =0;
    #250 reset=1;
    #300 $finish;
  end
    always #5 clk=~clk;
  
endmodule

syn down counter/tff_wave.vcd
$date
	Mon Jul 27 03:50:20 2026
$end
$version
	Icarus Verilog
$end
$timescale
	1s
$end
$scope module tb $end
$var wire 4 ! a [3:0] $end
$var reg 1 " clk $end
$var reg 1 # reset $end
$upscope $end
$enddefinitions $end
$comment Show the parameter values. $end
$dumpall
$end
#0
$dumpvars
x#
0"
bx !
$end
#5
1"
#10
0"
1#
#15
b1111 !
1"
#20
0"
#25
1"
#30
0"
0#
#35
b1110 !
1"
#40
0"
#45
b1101 !
1"
#50
0"
#55
b1100 !
1"
#60
0"
#65
b1011 !
1"
#70
0"
#75
b1010 !
1"
#80
0"
#85
b1001 !
1"
#90
0"
#95
b1000 !
1"
#100
0"
#105
b111 !
1"
#110
0"
#115
b110 !
1"
#120
0"
#125
b101 !
1"
#130
0"
#135
b100 !
1"
#140
0"
#145
b11 !
1"
#150
0"
#155
b10 !
1"
#160
0"
#165
b1 !
1"
#170
0"
#175
b0 !
1"
#180
0"
#185
b1111 !
1"
#190
0"
#195
b1110 !
1"
#200
0"
#205
b1101 !
1"
#210
0"
#215
b1100 !
1"
#220
0"
#225
b1011 !
1"
#230
0"
#235
b1010 !
1"
#240
0"
#245
b1001 !
1"
#250
0"
#255
b1000 !
1"
#260
0"
#265
b111 !
1"
#270
0"
#275
b110 !
1"
#280
0"
1#
#285
b1111 !
1"
